odoo/addons/ssi_hr_expense_account/README.rst
odoo/addons/ssi_hr_expense_account/__init__.py
odoo/addons/ssi_hr_expense_account/__manifest__.py
odoo/addons/ssi_hr_expense_account/data/approval_template_data.xml
odoo/addons/ssi_hr_expense_account/data/base_automation_data.xml
odoo/addons/ssi_hr_expense_account/data/ir_actions_server_data.xml
odoo/addons/ssi_hr_expense_account/data/ir_sequence_data.xml
odoo/addons/ssi_hr_expense_account/data/policy_template_data.xml
odoo/addons/ssi_hr_expense_account/data/sequence_template_data.xml
odoo/addons/ssi_hr_expense_account/i18n/ssi_hr_expense_account.pot
odoo/addons/ssi_hr_expense_account/models/__init__.py
odoo/addons/ssi_hr_expense_account/models/employee_expense_account.py
odoo/addons/ssi_hr_expense_account/models/employee_expense_account_type.py
odoo/addons/ssi_hr_expense_account/models/hr_expense_type.py
odoo/addons/ssi_hr_expense_account/models/hr_expense_type_product.py
odoo/addons/ssi_hr_expense_account/models/hr_expense_type_product_category.py
odoo/addons/ssi_hr_expense_account/security/ir.model.access.csv
odoo/addons/ssi_hr_expense_account/security/ir_module_category_data.xml
odoo/addons/ssi_hr_expense_account/security/ir_rule_data.xml
odoo/addons/ssi_hr_expense_account/security/res_group_data.xml
odoo/addons/ssi_hr_expense_account/static/description/icon.png
odoo/addons/ssi_hr_expense_account/static/description/icon_timesheet.png
odoo/addons/ssi_hr_expense_account/views/employee_expense_account_type_view.xml
odoo/addons/ssi_hr_expense_account/views/employee_expense_account_view.xml
odoo/addons/ssi_hr_expense_account/views/hr_expense_type_product_category_views.xml
odoo/addons/ssi_hr_expense_account/views/hr_expense_type_product_views.xml
odoo14_addon_ssi_hr_expense_account-14.0.1.4.0.dist-info/METADATA
odoo14_addon_ssi_hr_expense_account-14.0.1.4.0.dist-info/WHEEL
odoo14_addon_ssi_hr_expense_account-14.0.1.4.0.dist-info/top_level.txt
odoo14_addon_ssi_hr_expense_account-14.0.1.4.0.dist-info/RECORD
